{
  "students": [
    {
      "id": 2890767,
      "name": "Matt",
      "username": "MDShields7",
      "state": "active",
      "avatar_url": "https://secure.gravatar.com/avatar/6f45acb73d384fdb213fc93a76903048?s=80&d=identicon",
      "web_url": "https://gitlab.com/MDShields7"
    },
    {
      "id": 2890764,
      "name": "Chad Allen",
      "username": "chadvallen",
      "state": "active",
      "avatar_url": "https://secure.gravatar.com/avatar/37dc5e4e3a67e2c6bff209f0ba662605?s=80&d=identicon",
      "web_url": "https://gitlab.com/chadvallen"
    },
    {
      "id": 818376,
      "name": "Christian Ramos",
      "username": "chris12540",
      "state": "active",
      "avatar_url": "https://secure.gravatar.com/avatar/2d459d9dca4c09f15467f1bfb2432f39?s=80&d=identicon",
      "web_url": "https://gitlab.com/chris12540"
    },
    {
      "id": 2890773,
      "name": "danBohon",
      "username": "danBohon",
      "state": "active",
      "avatar_url": "https://secure.gravatar.com/avatar/eb7d4871227309a68ac89a377e4c84b4?s=80&d=identicon",
      "web_url": "https://gitlab.com/danBohon"
    },
    {
      "id": 2890768,
      "name": "Hunter Carrico",
      "username": "hmcarrico",
      "state": "active",
      "avatar_url": "https://secure.gravatar.com/avatar/bf06538fe548ae6e26bce60208946a08?s=80&d=identicon",
      "web_url": "https://gitlab.com/hmcarrico"
    },
    {
      "id": 2890762,
      "name": "jemilalghani",
      "username": "jemilalghani",
      "state": "active",
      "avatar_url": "https://secure.gravatar.com/avatar/6d28916457b346f88a9f4f04bd8f8f84?s=80&d=identicon",
      "web_url": "https://gitlab.com/jemilalghani"
    },
    {
      "id": 2890778,
      "name": "Justin Horton",
      "username": "justin.thomas13",
      "state": "active",
      "avatar_url": "https://secure.gravatar.com/avatar/ac5ba990ed9ca82096378a13eedf5bf6?s=80&d=identicon",
      "web_url": "https://gitlab.com/justin.thomas13"
    },
    {
      "id": 2890771,
      "name": "papakyle02",
      "username": "papakyle02",
      "state": "active",
      "avatar_url": "https://secure.gravatar.com/avatar/1d19087a0919a68630f6739a546a3805?s=80&d=identicon",
      "web_url": "https://gitlab.com/papakyle02"
    },
    {
      "id": 2890765,
      "name": "madi",
      "username": "rilakumma",
      "state": "active",
      "avatar_url": "https://secure.gravatar.com/avatar/4eb72a75464a7fce441d9bc9d8dbc022?s=80&d=identicon",
      "web_url": "https://gitlab.com/rilakumma"
    },
    {
      "id": 2890774,
      "name": "gillygilstrap",
      "username": "gillygilstrap",
      "state": "active",
      "avatar_url": "https://secure.gravatar.com/avatar/b0c7fe3663da9aad046efa09fd0a50e4?s=80&d=identicon",
      "web_url": "https://gitlab.com/gillygilstrap"
    },
    {
      "id": 2890770,
      "name": "slummit",
      "username": "slummit",
      "state": "active",
      "avatar_url": "https://secure.gravatar.com/avatar/83064193c86f050e1c3c8106d9d88f7a?s=80&d=identicon",
      "web_url": "https://gitlab.com/slummit"
    },
    {
      "id": 2890763,
      "name": "txomastea",
      "username": "txomastea",
      "state": "active",
      "avatar_url": "https://secure.gravatar.com/avatar/84ea42a6cdc48ad7e0a950a54b10ea3f?s=80&d=identicon",
      "web_url": "https://gitlab.com/txomastea"
    },
    {
      "id": 2890780,
      "name": "TCoXXV",
      "username": "TCoXXV",
      "state": "active",
      "avatar_url": "https://secure.gravatar.com/avatar/3a9231cc018ee038d24b75cfb225488a?s=80&d=identicon",
      "web_url": "https://gitlab.com/TCoXXV"
    },
    {
      "id": 2890769,
      "name": "tstrat",
      "username": "tstrat",
      "state": "active",
      "avatar_url": "https://secure.gravatar.com/avatar/95b191665ff1de4ffbe6bc8b1acf1e8c?s=80&d=identicon",
      "web_url": "https://gitlab.com/tstrat"
    },
    {
      "id": 2890772,
      "name": "Ethan Hess",
      "username": "EthanHess",
      "state": "active",
      "avatar_url": "https://secure.gravatar.com/avatar/6c55042c2d21f9251bf647dd8ee6670e?s=80&d=identicon",
      "web_url": "https://gitlab.com/EthanHess"
    },
    {
      "id": 2890766,
      "name": "npulver00",
      "username": "npulver00",
      "state": "active",
      "avatar_url": "https://secure.gravatar.com/avatar/9a1f95b4af6542beaa19f1cc9f3c99d0?s=80&d=identicon",
      "web_url": "https://gitlab.com/npulver00"
    },
    {
      "id": 2937261,
      "name": "yetiwords",
      "username": "yetiwords",
      "state": "active",
      "avatar_url": "https://secure.gravatar.com/avatar/c7015978719bb62b2a5507cff829772b?s=80&d=identicon",
      "web_url": "https://gitlab.com/yetiwords"
    },
    {
      "id": 2937260,
      "name": "Jacob Bralish",
      "username": "JacobTBralish",
      "state": "active",
      "avatar_url": "https://secure.gravatar.com/avatar/22473f0f679b1e8bd0c7b254efeededf?s=80&d=identicon",
      "web_url": "https://gitlab.com/JacobTBralish"
    },
    {
      "id": 2937266,
      "name": "Sean Parmar",
      "username": "Parmesanio",
      "state": "active",
      "avatar_url": "https://secure.gravatar.com/avatar/14c552a8d65db7cfabef60c056b990bd?s=80&d=identicon",
      "web_url": "https://gitlab.com/Parmesanio"
    },
    {
      "id": 2937360,
      "name": "KaylinAnn",
      "username": "KaylinAnn",
      "state": "active",
      "avatar_url": "https://secure.gravatar.com/avatar/d96ffe332301c9db077b998a27a8f664?s=80&d=identicon",
      "web_url": "https://gitlab.com/KaylinAnn"
    },
    {
      "id": 2937587,
      "name": "Aisha Toulegenova",
      "username": "aetoule",
      "state": "active",
      "avatar_url": "https://secure.gravatar.com/avatar/2adc6449e7b7180b92fe880cc47ddb06?s=80&d=identicon",
      "web_url": "https://gitlab.com/aetoule"
    },
    {
      "id": 2954357,
      "name": "arisztid21",
      "username": "arisztid21",
      "state": "active",
      "avatar_url": "https://secure.gravatar.com/avatar/da6d99659df49ea816869e9133d7f001?s=80&d=identicon",
      "web_url": "https://gitlab.com/arisztid21"
    },
    {
      "id": 2954361,
      "name": "Jordan",
      "username": "jordanutz",
      "state": "active",
      "avatar_url": "https://secure.gravatar.com/avatar/29476eb2f927bc211eb0814237dd75eb?s=80&d=identicon",
      "web_url": "https://gitlab.com/jordanutz"
    },
    {
      "id": 2954358,
      "name": "DanielGomez1022",
      "username": "DanielGomez1022",
      "state": "active",
      "avatar_url": "https://secure.gravatar.com/avatar/626cd240d27606b8c6d514ae12fdbd46?s=80&d=identicon",
      "web_url": "https://gitlab.com/DanielGomez1022"
    },
    {
      "id": 2954360,
      "name": "Austin Grubb",
      "username": "austingrubb",
      "state": "active",
      "avatar_url": "https://secure.gravatar.com/avatar/b48f73f6a61a961905f1f6f769f4929b?s=80&d=identicon",
      "web_url": "https://gitlab.com/austingrubb"
    }
  ]
}